openbm/.pytest_cache/.gitignore
openbm/.pytest_cache/README.md
openbm/.pytest_cache/v/cache/nodeids
openbm/.pytest_cache/v/cache/stepwise
openbm/bin/activate
openbm/bin/activate.csh
openbm/bin/activate.fish
openbm/bin/activate_this.py
openbm/bin/circuits.bench
openbm/bin/circuits.web
openbm/bin/easy_install
openbm/bin/easy_install-2.7
openbm/bin/htpasswd
openbm/bin/pcreate
openbm/bin/pdistreport
openbm/bin/pip
openbm/bin/pip2
openbm/bin/pip2.7
openbm/bin/prequest
openbm/bin/proutes
openbm/bin/pserve
openbm/bin/pshell
openbm/bin/ptweens
openbm/bin/pviews
openbm/bin/python
openbm/bin/python2
openbm/bin/python2.7
openbm/bin/rpyc_classic.py
openbm/bin/rpyc_registry.py
openbm/bin/rst2html.py
openbm/bin/rst2latex.py
openbm/bin/rst2man.py
openbm/bin/rst2odt.py
openbm/bin/rst2odt_prepstyles.py
openbm/bin/rst2pseudoxml.py
openbm/bin/rst2s5.py
openbm/bin/rst2xetex.py
openbm/bin/rst2xml.py
openbm/bin/rstpep2html.py
openbm/dat a/gnodes.db
openbm/dat a/joblogs/Prueba1R163722340
openbm/dat a/joblogs/Prueba1R166629680
openbm/dat a/joblogs/Prueba1R188677140
openbm/dat a/joblogs/Prueba1R189761400
openbm/dat a/joblogs/Prueba1R189764450
openbm/dat a/joblogs/Prueba_plan_1minI10508400
openbm/dat a/joblogs/Prueba_plan_1minI10508460
openbm/dat a/joblogs/Prueba_plan_1minI10508520
openbm/dat a/joblogs/Prueba_plan_1minI10508580
openbm/dat a/joblogs/Prueba_plan_1minI10508640
openbm/dat a/joblogs/Prueba_plan_1minI10508760
openbm/dat a/joblogs/Prueba_plan_1minI10508820
openbm/dat a/joblogs/Prueba_plan_1minI10508880
openbm/dat a/joblogs/Prueba_plan_1minI10509000
openbm/dat a/joblogs/Prueba_plan_1minI10509120
openbm/dat a/joblogs/Prueba_plan_1minI10509300
openbm/dat a/joblogs/Prueba_plan_1minI10509960
openbm/dat a/joblogs/Prueba_plan_1minI10510860
openbm/dat a/joblogs/Prueba_plan_1minI10511160
openbm/dat a/joblogs/Prueba_plan_1minI5503540
openbm/dat a/joblogs/Prueba_plan_1minI5503570
openbm/dat a/joblogs/Prueba_plan_1minI7703540
openbm/dat a/joblogs/Prueba_plan_1minI78-82859
openbm-0.1.0.dist-info/entry_points.txt
openbm-0.1.0.dist-info/WHEEL
openbm-0.1.0.dist-info/METADATA
openbm-0.1.0.dist-info/RECORD
