Metadata-Version: 2.1
Name: openbm
Version: 0.1.0
Summary: OpenBatchManager is a distributed, high performant, fault tolerant job scheduler
Home-page: UNKNOWN
License: Apache-2.0
Author: Oscar Curero
Author-email: oscar@curero.es
Requires-Python: >=3.6,<4.0
Classifier: License :: OSI Approved :: Apache Software License
Classifier: Programming Language :: Python :: 3
Classifier: Programming Language :: Python :: 3.6
Classifier: Programming Language :: Python :: 3.7
Requires-Dist: aioprocessing (>=1.0,<2.0)
Requires-Dist: apscheduler (>=3.5.1,<4.0.0)
Requires-Dist: boolrule (>=0.3.0,<0.4.0)
Requires-Dist: cheroot (>=6.3,<7.0)
Requires-Dist: click (>=6.7,<7.0)
Requires-Dist: coverage (>=4,<5)
Requires-Dist: dataclasses (>=0.6.0,<0.7.0)
Requires-Dist: decorator (>=4.3,<5.0)
Requires-Dist: networkx (>=2.1,<3.0)
Requires-Dist: notifiers (>=0.7.4,<0.8.0)
Requires-Dist: pendulum (>=2.0,<3.0)
Requires-Dist: psutil (>=5.4,<6.0)
Requires-Dist: pydblite (>=3.0,<4.0)
Requires-Dist: pyramid (>=1.9,<2.0)
Requires-Dist: pyramid_exclog (>=1.0,<2.0)
Requires-Dist: pysyncobj (>=0.3.3,<0.4.0)
Requires-Dist: pytest-lazy-fixture (>=0.5.1,<0.6.0)
Requires-Dist: pyyaml (>=3.12,<4.0)
Requires-Dist: requests (>=2.18,<3.0)
Requires-Dist: schema (>=0.6.7,<0.7.0)
Requires-Dist: sqlalchemy-querybuilder (>=0.1.2,<0.2.0)
Requires-Dist: stevedore (>=1.28,<2.0)
Requires-Dist: tblib (>=1.3,<2.0)
Requires-Dist: websockets (>=5.0,<6.0)
Requires-Dist: zope.sqlalchemy (>=1.0,<2.0)
